{
    "data": [
        {
            "traceID": "018119f23bec1d7c",
            "spans": [
                {
                    "traceID": "018119f23bec1d7c",
                    "spanID": "6fc7aae9c9180a62",
                    "flags": 1,
                    "operationName": "/profile.Profile/GetProfiles",
                    "references": [
                        {
                            "refType": "CHILD_OF",
                            "traceID": "018119f23bec1d7c",
                            "spanID": "0cdd2fc4732ce78d"
                        }
                    ],
                    "startTime": 1655753663679088,
                    "duration": 3244,
                    "tags": [
                        {
                            "key": "span.kind",
                            "type": "string",
                            "value": "server"
                        },
                        {
                            "key": "component",
                            "type": "string",
                            "value": "gRPC"
                        },
                        {
                            "key": "internal.span.format",
                            "type": "string",
                            "value": "proto"
                        }
                    ],
                    "logs": [],
                    "processID": "p1",
                    "warnings": null
                },
                {
                    "traceID": "018119f23bec1d7c",
                    "spanID": "35a169dc41fa0a6e",
                    "flags": 1,
                    "operationName": "/geo.Geo/Nearby",
                    "references": [
                        {
                            "refType": "CHILD_OF",
                            "traceID": "018119f23bec1d7c",
                            "spanID": "55f19af6f103c818"
                        }
                    ],
                    "startTime": 1655753663645490,
                    "duration": 417,
                    "tags": [
                        {
                            "key": "span.kind",
                            "type": "string",
                            "value": "server"
                        },
                        {
                            "key": "component",
                            "type": "string",
                            "value": "gRPC"
                        },
                        {
                            "key": "internal.span.format",
                            "type": "string",
                            "value": "proto"
                        }
                    ],
                    "logs": [],
                    "processID": "p2",
                    "warnings": null
                },
                {
                    "traceID": "018119f23bec1d7c",
                    "spanID": "69fc53cd05e2e34d",
                    "flags": 1,
                    "operationName": "/search.Search/Nearby",
                    "references": [
                        {
                            "refType": "CHILD_OF",
                            "traceID": "018119f23bec1d7c",
                            "spanID": "018119f23bec1d7c"
                        }
                    ],
                    "startTime": 1655753663641838,
                    "duration": 17654,
                    "tags": [
                        {
                            "key": "span.kind",
                            "type": "string",
                            "value": "client"
                        },
                        {
                            "key": "component",
                            "type": "string",
                            "value": "gRPC"
                        },
                        {
                            "key": "internal.span.format",
                            "type": "string",
                            "value": "proto"
                        }
                    ],
                    "logs": [],
                    "processID": "p3",
                    "warnings": null
                },
                {
                    "traceID": "018119f23bec1d7c",
                    "spanID": "2d9f4d68c3926b54",
                    "flags": 1,
                    "operationName": "/reservation.Reservation/CheckAvailability",
                    "references": [
                        {
                            "refType": "CHILD_OF",
                            "traceID": "018119f23bec1d7c",
                            "spanID": "018119f23bec1d7c"
                        }
                    ],
                    "startTime": 1655753663660076,
                    "duration": 17994,
                    "tags": [
                        {
                            "key": "component",
                            "type": "string",
                            "value": "gRPC"
                        },
                        {
                            "key": "span.kind",
                            "type": "string",
                            "value": "client"
                        },
                        {
                            "key": "internal.span.format",
                            "type": "string",
                            "value": "proto"
                        }
                    ],
                    "logs": [],
                    "processID": "p3",
                    "warnings": null
                },
                {
                    "traceID": "018119f23bec1d7c",
                    "spanID": "0cdd2fc4732ce78d",
                    "flags": 1,
                    "operationName": "/profile.Profile/GetProfiles",
                    "references": [
                        {
                            "refType": "CHILD_OF",
                            "traceID": "018119f23bec1d7c",
                            "spanID": "018119f23bec1d7c"
                        }
                    ],
                    "startTime": 1655753663678209,
                    "duration": 4858,
                    "tags": [
                        {
                            "key": "span.kind",
                            "type": "string",
                            "value": "client"
                        },
                        {
                            "key": "component",
                            "type": "string",
                            "value": "gRPC"
                        },
                        {
                            "key": "internal.span.format",
                            "type": "string",
                            "value": "proto"
                        }
                    ],
                    "logs": [],
                    "processID": "p3",
                    "warnings": null
                },
                {
                    "traceID": "018119f23bec1d7c",
                    "spanID": "018119f23bec1d7c",
                    "flags": 1,
                    "operationName": "HTTP GET /hotels",
                    "references": [],
                    "startTime": 1655753663641206,
                    "duration": 42104,
                    "tags": [
                        {
                            "key": "sampler.type",
                            "type": "string",
                            "value": "probabilistic"
                        },
                        {
                            "key": "sampler.param",
                            "type": "float64",
                            "value": 0.3
                        },
                        {
                            "key": "span.kind",
                            "type": "string",
                            "value": "server"
                        },
                        {
                            "key": "http.method",
                            "type": "string",
                            "value": "GET"
                        },
                        {
                            "key": "http.url",
                            "type": "string",
                            "value": "/hotels?inDate=2015-04-17\u0026outDate=2015-04-24\u0026lat=38.082\u0026lon=-121.943"
                        },
                        {
                            "key": "component",
                            "type": "string",
                            "value": "net/http"
                        },
                        {
                            "key": "http.status_code",
                            "type": "int64",
                            "value": 200
                        },
                        {
                            "key": "internal.span.format",
                            "type": "string",
                            "value": "proto"
                        }
                    ],
                    "logs": [],
                    "processID": "p3",
                    "warnings": null
                },
                {
                    "traceID": "018119f23bec1d7c",
                    "spanID": "55f19af6f103c818",
                    "flags": 1,
                    "operationName": "/geo.Geo/Nearby",
                    "references": [
                        {
                            "refType": "CHILD_OF",
                            "traceID": "018119f23bec1d7c",
                            "spanID": "74d29fec2edeb754"
                        }
                    ],
                    "startTime": 1655753663644570,
                    "duration": 2380,
                    "tags": [
                        {
                            "key": "component",
                            "type": "string",
                            "value": "gRPC"
                        },
                        {
                            "key": "span.kind",
                            "type": "string",
                            "value": "client"
                        },
                        {
                            "key": "internal.span.format",
                            "type": "string",
                            "value": "proto"
                        }
                    ],
                    "logs": [],
                    "processID": "p4",
                    "warnings": [
                        "clock skew adjustment disabled; not applying calculated delta of -1.271ms"
                    ]
                },
                {
                    "traceID": "018119f23bec1d7c",
                    "spanID": "3694b6c15c5bc288",
                    "flags": 1,
                    "operationName": "/rate.Rate/GetRates",
                    "references": [
                        {
                            "refType": "CHILD_OF",
                            "traceID": "018119f23bec1d7c",
                            "spanID": "74d29fec2edeb754"
                        }
                    ],
                    "startTime": 1655753663647229,
                    "duration": 12357,
                    "tags": [
                        {
                            "key": "span.kind",
                            "type": "string",
                            "value": "client"
                        },
                        {
                            "key": "component",
                            "type": "string",
                            "value": "gRPC"
                        },
                        {
                            "key": "internal.span.format",
                            "type": "string",
                            "value": "proto"
                        }
                    ],
                    "logs": [],
                    "processID": "p4",
                    "warnings": [
                        "clock skew adjustment disabled; not applying calculated delta of -1.271ms"
                    ]
                },
                {
                    "traceID": "018119f23bec1d7c",
                    "spanID": "74d29fec2edeb754",
                    "flags": 1,
                    "operationName": "/search.Search/Nearby",
                    "references": [
                        {
                            "refType": "CHILD_OF",
                            "traceID": "018119f23bec1d7c",
                            "spanID": "69fc53cd05e2e34d"
                        }
                    ],
                    "startTime": 1655753663644173,
                    "duration": 15526,
                    "tags": [
                        {
                            "key": "span.kind",
                            "type": "string",
                            "value": "server"
                        },
                        {
                            "key": "component",
                            "type": "string",
                            "value": "gRPC"
                        },
                        {
                            "key": "internal.span.format",
                            "type": "string",
                            "value": "proto"
                        }
                    ],
                    "logs": [],
                    "processID": "p4",
                    "warnings": [
                        "clock skew adjustment disabled; not applying calculated delta of -1.271ms"
                    ]
                },
                {
                    "traceID": "018119f23bec1d7c",
                    "spanID": "53efa01e0eee5059",
                    "flags": 1,
                    "operationName": "/rate.Rate/GetRates",
                    "references": [
                        {
                            "refType": "CHILD_OF",
                            "traceID": "018119f23bec1d7c",
                            "spanID": "3694b6c15c5bc288"
                        }
                    ],
                    "startTime": 1655753663648621,
                    "duration": 10112,
                    "tags": [
                        {
                            "key": "span.kind",
                            "type": "string",
                            "value": "server"
                        },
                        {
                            "key": "component",
                            "type": "string",
                            "value": "gRPC"
                        },
                        {
                            "key": "internal.span.format",
                            "type": "string",
                            "value": "proto"
                        }
                    ],
                    "logs": [],
                    "processID": "p5",
                    "warnings": null
                },
                {
                    "traceID": "018119f23bec1d7c",
                    "spanID": "31ff482c921d02b1",
                    "flags": 1,
                    "operationName": "/reservation.Reservation/CheckAvailability",
                    "references": [
                        {
                            "refType": "CHILD_OF",
                            "traceID": "018119f23bec1d7c",
                            "spanID": "2d9f4d68c3926b54"
                        }
                    ],
                    "startTime": 1655753663662616,
                    "duration": 15531,
                    "tags": [
                        {
                            "key": "span.kind",
                            "type": "string",
                            "value": "server"
                        },
                        {
                            "key": "component",
                            "type": "string",
                            "value": "gRPC"
                        },
                        {
                            "key": "internal.span.format",
                            "type": "string",
                            "value": "proto"
                        }
                    ],
                    "logs": [],
                    "processID": "p6",
                    "warnings": [
                        "clock skew adjustment disabled; not applying calculated delta of -1.3085ms"
                    ]
                }
            ],
            "processes": {
                "p1": {
                    "serviceName": "profile",
                    "tags": [
                        {
                            "key": "hostname",
                            "type": "string",
                            "value": "profile-74f799494b-vftn2"
                        },
                        {
                            "key": "ip",
                            "type": "string",
                            "value": "10.0.2.207"
                        },
                        {
                            "key": "jaeger.version",
                            "type": "string",
                            "value": "Go-2.11.2"
                        }
                    ]
                },
                "p2": {
                    "serviceName": "geo",
                    "tags": [
                        {
                            "key": "hostname",
                            "type": "string",
                            "value": "geo-6455488cd8-9pdxx"
                        },
                        {
                            "key": "ip",
                            "type": "string",
                            "value": "10.0.1.61"
                        },
                        {
                            "key": "jaeger.version",
                            "type": "string",
                            "value": "Go-2.11.2"
                        }
                    ]
                },
                "p3": {
                    "serviceName": "frontend",
                    "tags": [
                        {
                            "key": "hostname",
                            "type": "string",
                            "value": "frontend-6bfdb55ffc-qbc8v"
                        },
                        {
                            "key": "ip",
                            "type": "string",
                            "value": "10.0.2.221"
                        },
                        {
                            "key": "jaeger.version",
                            "type": "string",
                            "value": "Go-2.11.2"
                        }
                    ]
                },
                "p4": {
                    "serviceName": "search",
                    "tags": [
                        {
                            "key": "hostname",
                            "type": "string",
                            "value": "search-7b976b6966-mnrrt"
                        },
                        {
                            "key": "ip",
                            "type": "string",
                            "value": "10.0.1.142"
                        },
                        {
                            "key": "jaeger.version",
                            "type": "string",
                            "value": "Go-2.11.2"
                        }
                    ]
                },
                "p5": {
                    "serviceName": "rate",
                    "tags": [
                        {
                            "key": "hostname",
                            "type": "string",
                            "value": "rate-86bd69bdcd-z28hz"
                        },
                        {
                            "key": "ip",
                            "type": "string",
                            "value": "10.0.1.3"
                        },
                        {
                            "key": "jaeger.version",
                            "type": "string",
                            "value": "Go-2.11.2"
                        }
                    ]
                },
                "p6": {
                    "serviceName": "reservation",
                    "tags": [
                        {
                            "key": "hostname",
                            "type": "string",
                            "value": "reservation-dc5557677-9t7xw"
                        },
                        {
                            "key": "ip",
                            "type": "string",
                            "value": "10.0.1.212"
                        },
                        {
                            "key": "jaeger.version",
                            "type": "string",
                            "value": "Go-2.11.2"
                        }
                    ]
                }
            },
            "warnings": null
        }
    ],
    "total": 0,
    "limit": 0,
    "offset": 0,
    "errors": null
}