{
    "data": [
        {
            "traceID": "573c722ea5ec3c45",
            "spans": [
                {
                    "traceID": "573c722ea5ec3c45",
                    "spanID": "98e71c3b30a45ec2",
                    "flags": 1,
                    "operationName": "RedisInsert",
                    "references": [
                        {
                            "refType": "CHILD_OF",
                            "traceID": "573c722ea5ec3c45",
                            "spanID": "f1608cd20a3b60fd"
                        }
                    ],
                    "startTime": 1695223402257021,
                    "duration": 697,
                    "tags": [
                        {
                            "key": "internal.span.format",
                            "type": "string",
                            "value": "proto"
                        }
                    ],
                    "logs": [],
                    "processID": "p1",
                    "warnings": null
                },
                {
                    "traceID": "573c722ea5ec3c45",
                    "spanID": "f1608cd20a3b60fd",
                    "flags": 1,
                    "operationName": "UploadRating",
                    "references": [
                        {
                            "refType": "CHILD_OF",
                            "traceID": "573c722ea5ec3c45",
                            "spanID": "736fc26fa6ccc48f"
                        }
                    ],
                    "startTime": 1695223402256853,
                    "duration": 8324,
                    "tags": [
                        {
                            "key": "internal.span.format",
                            "type": "string",
                            "value": "proto"
                        }
                    ],
                    "logs": [],
                    "processID": "p1",
                    "warnings": null
                },
                {
                    "traceID": "573c722ea5ec3c45",
                    "spanID": "658ed821ec58ae7c",
                    "flags": 1,
                    "operationName": "MongoInsertReview",
                    "references": [
                        {
                            "refType": "CHILD_OF",
                            "traceID": "573c722ea5ec3c45",
                            "spanID": "f127da2fe75209a0"
                        }
                    ],
                    "startTime": 1695223402261634,
                    "duration": 293,
                    "tags": [
                        {
                            "key": "internal.span.format",
                            "type": "string",
                            "value": "proto"
                        }
                    ],
                    "logs": [],
                    "processID": "p2",
                    "warnings": null
                },
                {
                    "traceID": "573c722ea5ec3c45",
                    "spanID": "f127da2fe75209a0",
                    "flags": 1,
                    "operationName": "StoreReview",
                    "references": [
                        {
                            "refType": "CHILD_OF",
                            "traceID": "573c722ea5ec3c45",
                            "spanID": "0f1e0bc79aac9789"
                        }
                    ],
                    "startTime": 1695223402261613,
                    "duration": 333,
                    "tags": [
                        {
                            "key": "internal.span.format",
                            "type": "string",
                            "value": "proto"
                        }
                    ],
                    "logs": [],
                    "processID": "p2",
                    "warnings": null
                },
                {
                    "traceID": "573c722ea5ec3c45",
                    "spanID": "3025381710d931f0",
                    "flags": 1,
                    "operationName": "MmcGetUserId",
                    "references": [
                        {
                            "refType": "CHILD_OF",
                            "traceID": "573c722ea5ec3c45",
                            "spanID": "84baa9d0d0994b12"
                        }
                    ],
                    "startTime": 1695223402255302,
                    "duration": 440,
                    "tags": [
                        {
                            "key": "internal.span.format",
                            "type": "string",
                            "value": "proto"
                        }
                    ],
                    "logs": [],
                    "processID": "p3",
                    "warnings": null
                },
                {
                    "traceID": "573c722ea5ec3c45",
                    "spanID": "84baa9d0d0994b12",
                    "flags": 1,
                    "operationName": "UploadUserWithUsername",
                    "references": [
                        {
                            "refType": "CHILD_OF",
                            "traceID": "573c722ea5ec3c45",
                            "spanID": "6016aaf50cca53b0"
                        }
                    ],
                    "startTime": 1695223402255281,
                    "duration": 2625,
                    "tags": [
                        {
                            "key": "internal.span.format",
                            "type": "string",
                            "value": "proto"
                        }
                    ],
                    "logs": [],
                    "processID": "p3",
                    "warnings": null
                },
                {
                    "traceID": "573c722ea5ec3c45",
                    "spanID": "d22071b02bd9abba",
                    "flags": 1,
                    "operationName": "RedisUpdate",
                    "references": [
                        {
                            "refType": "CHILD_OF",
                            "traceID": "573c722ea5ec3c45",
                            "spanID": "fd19a9328499d916"
                        }
                    ],
                    "startTime": 1695223402263697,
                    "duration": 505,
                    "tags": [
                        {
                            "key": "internal.span.format",
                            "type": "string",
                            "value": "proto"
                        }
                    ],
                    "logs": [],
                    "processID": "p4",
                    "warnings": null
                },
                {
                    "traceID": "573c722ea5ec3c45",
                    "spanID": "fd19a9328499d916",
                    "flags": 1,
                    "operationName": "UploadUserReview",
                    "references": [
                        {
                            "refType": "CHILD_OF",
                            "traceID": "573c722ea5ec3c45",
                            "spanID": "0f1e0bc79aac9789"
                        }
                    ],
                    "startTime": 1695223402261406,
                    "duration": 2808,
                    "tags": [
                        {
                            "key": "internal.span.format",
                            "type": "string",
                            "value": "proto"
                        }
                    ],
                    "logs": [],
                    "processID": "p4",
                    "warnings": null
                },
                {
                    "traceID": "573c722ea5ec3c45",
                    "spanID": "847c59d5c7a26846",
                    "flags": 1,
                    "operationName": "MongoFindUser",
                    "references": [
                        {
                            "refType": "CHILD_OF",
                            "traceID": "573c722ea5ec3c45",
                            "spanID": "fd19a9328499d916"
                        }
                    ],
                    "startTime": 1695223402261428,
                    "duration": 2790,
                    "tags": [
                        {
                            "key": "internal.span.format",
                            "type": "string",
                            "value": "proto"
                        }
                    ],
                    "logs": [],
                    "processID": "p4",
                    "warnings": null
                },
                {
                    "traceID": "573c722ea5ec3c45",
                    "spanID": "6f27822712325e55",
                    "flags": 1,
                    "operationName": "MongoUpdate",
                    "references": [
                        {
                            "refType": "CHILD_OF",
                            "traceID": "573c722ea5ec3c45",
                            "spanID": "fd19a9328499d916"
                        }
                    ],
                    "startTime": 1695223402262718,
                    "duration": 954,
                    "tags": [
                        {
                            "key": "internal.span.format",
                            "type": "string",
                            "value": "proto"
                        }
                    ],
                    "logs": [],
                    "processID": "p4",
                    "warnings": null
                },
                {
                    "traceID": "573c722ea5ec3c45",
                    "spanID": "6cde0d6a1d872f27",
                    "flags": 1,
                    "operationName": "MongoUpdate.",
                    "references": [
                        {
                            "refType": "CHILD_OF",
                            "traceID": "573c722ea5ec3c45",
                            "spanID": "b69bc06d5602027d"
                        }
                    ],
                    "startTime": 1695223402262742,
                    "duration": 577,
                    "tags": [
                        {
                            "key": "internal.span.format",
                            "type": "string",
                            "value": "proto"
                        }
                    ],
                    "logs": [],
                    "processID": "p5",
                    "warnings": null
                },
                {
                    "traceID": "573c722ea5ec3c45",
                    "spanID": "b5fad5e46688d9b7",
                    "flags": 1,
                    "operationName": "RedisUpdate",
                    "references": [
                        {
                            "refType": "CHILD_OF",
                            "traceID": "573c722ea5ec3c45",
                            "spanID": "b69bc06d5602027d"
                        }
                    ],
                    "startTime": 1695223402263350,
                    "duration": 828,
                    "tags": [
                        {
                            "key": "internal.span.format",
                            "type": "string",
                            "value": "proto"
                        }
                    ],
                    "logs": [],
                    "processID": "p5",
                    "warnings": null
                },
                {
                    "traceID": "573c722ea5ec3c45",
                    "spanID": "b69bc06d5602027d",
                    "flags": 1,
                    "operationName": "UploadMovieReview",
                    "references": [
                        {
                            "refType": "CHILD_OF",
                            "traceID": "573c722ea5ec3c45",
                            "spanID": "0f1e0bc79aac9789"
                        }
                    ],
                    "startTime": 1695223402262123,
                    "duration": 2071,
                    "tags": [
                        {
                            "key": "internal.span.format",
                            "type": "string",
                            "value": "proto"
                        }
                    ],
                    "logs": [],
                    "processID": "p5",
                    "warnings": null
                },
                {
                    "traceID": "573c722ea5ec3c45",
                    "spanID": "a02684706f40786b",
                    "flags": 1,
                    "operationName": "MongoFindMovie",
                    "references": [
                        {
                            "refType": "CHILD_OF",
                            "traceID": "573c722ea5ec3c45",
                            "spanID": "b69bc06d5602027d"
                        }
                    ],
                    "startTime": 1695223402262148,
                    "duration": 2051,
                    "tags": [
                        {
                            "key": "internal.span.format",
                            "type": "string",
                            "value": "proto"
                        }
                    ],
                    "logs": [],
                    "processID": "p5",
                    "warnings": null
                },
                {
                    "traceID": "573c722ea5ec3c45",
                    "spanID": "579a8adef62a8ac1",
                    "flags": 1,
                    "operationName": "/wrk2-api/review/compose",
                    "references": [
                        {
                            "refType": "CHILD_OF",
                            "traceID": "573c722ea5ec3c45",
                            "spanID": "573c722ea5ec3c45"
                        }
                    ],
                    "startTime": 1695223402254925,
                    "duration": 10674,
                    "tags": [
                        {
                            "key": "component",
                            "type": "string",
                            "value": "nginx"
                        },
                        {
                            "key": "nginx.worker_pid",
                            "type": "string",
                            "value": "11"
                        },
                        {
                            "key": "peer.address",
                            "type": "string",
                            "value": "172.18.0.1:55836"
                        },
                        {
                            "key": "http.method",
                            "type": "string",
                            "value": "POST"
                        },
                        {
                            "key": "http.url",
                            "type": "string",
                            "value": "http://localhost:8080/wrk2-api/review/compose/wrk2-api/review/compose"
                        },
                        {
                            "key": "http.host",
                            "type": "string",
                            "value": "localhost:8080"
                        },
                        {
                            "key": "http.status_code",
                            "type": "int64",
                            "value": 200
                        },
                        {
                            "key": "http.status_line",
                            "type": "string",
                            "value": ""
                        },
                        {
                            "key": "internal.span.format",
                            "type": "string",
                            "value": "proto"
                        }
                    ],
                    "logs": [],
                    "processID": "p6",
                    "warnings": null
                },
                {
                    "traceID": "573c722ea5ec3c45",
                    "spanID": "573c722ea5ec3c45",
                    "flags": 1,
                    "operationName": "/wrk2-api/review/compose",
                    "references": [],
                    "startTime": 1695223402254000,
                    "duration": 11600,
                    "tags": [
                        {
                            "key": "sampler.type",
                            "type": "string",
                            "value": "const"
                        },
                        {
                            "key": "sampler.param",
                            "type": "bool",
                            "value": true
                        },
                        {
                            "key": "http.status_code",
                            "type": "int64",
                            "value": 200
                        },
                        {
                            "key": "http.status_line",
                            "type": "string",
                            "value": ""
                        },
                        {
                            "key": "component",
                            "type": "string",
                            "value": "nginx"
                        },
                        {
                            "key": "nginx.worker_pid",
                            "type": "string",
                            "value": "11"
                        },
                        {
                            "key": "peer.address",
                            "type": "string",
                            "value": "172.18.0.1:55836"
                        },
                        {
                            "key": "http.method",
                            "type": "string",
                            "value": "POST"
                        },
                        {
                            "key": "http.url",
                            "type": "string",
                            "value": "http://localhost:8080/wrk2-api/review/compose/wrk2-api/review/compose"
                        },
                        {
                            "key": "http.host",
                            "type": "string",
                            "value": "localhost:8080"
                        },
                        {
                            "key": "internal.span.format",
                            "type": "string",
                            "value": "proto"
                        }
                    ],
                    "logs": [],
                    "processID": "p6",
                    "warnings": null
                },
                {
                    "traceID": "573c722ea5ec3c45",
                    "spanID": "6016aaf50cca53b0",
                    "flags": 1,
                    "operationName": "ComposeReview",
                    "references": [
                        {
                            "refType": "CHILD_OF",
                            "traceID": "573c722ea5ec3c45",
                            "spanID": "579a8adef62a8ac1"
                        }
                    ],
                    "startTime": 1695223402254985,
                    "duration": 10551,
                    "tags": [
                        {
                            "key": "internal.span.format",
                            "type": "string",
                            "value": "proto"
                        }
                    ],
                    "logs": [],
                    "processID": "p6",
                    "warnings": null
                },
                {
                    "traceID": "573c722ea5ec3c45",
                    "spanID": "17ff2c693254e753",
                    "flags": 1,
                    "operationName": "UploadText",
                    "references": [
                        {
                            "refType": "CHILD_OF",
                            "traceID": "573c722ea5ec3c45",
                            "spanID": "1ea3c613556d5a82"
                        }
                    ],
                    "startTime": 1695223402255767,
                    "duration": 1399,
                    "tags": [
                        {
                            "key": "internal.span.format",
                            "type": "string",
                            "value": "proto"
                        }
                    ],
                    "logs": [],
                    "processID": "p7",
                    "warnings": null
                },
                {
                    "traceID": "573c722ea5ec3c45",
                    "spanID": "437a6acba0ed953b",
                    "flags": 1,
                    "operationName": "UploadMovieId",
                    "references": [
                        {
                            "refType": "CHILD_OF",
                            "traceID": "573c722ea5ec3c45",
                            "spanID": "736fc26fa6ccc48f"
                        }
                    ],
                    "startTime": 1695223402256707,
                    "duration": 598,
                    "tags": [
                        {
                            "key": "internal.span.format",
                            "type": "string",
                            "value": "proto"
                        }
                    ],
                    "logs": [],
                    "processID": "p7",
                    "warnings": null
                },
                {
                    "traceID": "573c722ea5ec3c45",
                    "spanID": "43a8d25c5ea02ade",
                    "flags": 1,
                    "operationName": "UploadUserId",
                    "references": [
                        {
                            "refType": "CHILD_OF",
                            "traceID": "573c722ea5ec3c45",
                            "spanID": "84baa9d0d0994b12"
                        }
                    ],
                    "startTime": 1695223402256091,
                    "duration": 1390,
                    "tags": [
                        {
                            "key": "internal.span.format",
                            "type": "string",
                            "value": "proto"
                        }
                    ],
                    "logs": [],
                    "processID": "p7",
                    "warnings": null
                },
                {
                    "traceID": "573c722ea5ec3c45",
                    "spanID": "4f78616159f55099",
                    "flags": 1,
                    "operationName": "UploadUniqueId",
                    "references": [
                        {
                            "refType": "CHILD_OF",
                            "traceID": "573c722ea5ec3c45",
                            "spanID": "031cc469092cf536"
                        }
                    ],
                    "startTime": 1695223402257035,
                    "duration": 1697,
                    "tags": [
                        {
                            "key": "internal.span.format",
                            "type": "string",
                            "value": "proto"
                        }
                    ],
                    "logs": [],
                    "processID": "p7",
                    "warnings": null
                },
                {
                    "traceID": "573c722ea5ec3c45",
                    "spanID": "0f1e0bc79aac9789",
                    "flags": 1,
                    "operationName": "UploadRating",
                    "references": [
                        {
                            "refType": "CHILD_OF",
                            "traceID": "573c722ea5ec3c45",
                            "spanID": "f1608cd20a3b60fd"
                        }
                    ],
                    "startTime": 1695223402257111,
                    "duration": 7650,
                    "tags": [
                        {
                            "key": "internal.span.format",
                            "type": "string",
                            "value": "proto"
                        }
                    ],
                    "logs": [],
                    "processID": "p7",
                    "warnings": null
                },
                {
                    "traceID": "573c722ea5ec3c45",
                    "spanID": "74be494a6b48444d",
                    "flags": 1,
                    "operationName": "MmcGetMovieId",
                    "references": [
                        {
                            "refType": "CHILD_OF",
                            "traceID": "573c722ea5ec3c45",
                            "spanID": "736fc26fa6ccc48f"
                        }
                    ],
                    "startTime": 1695223402256059,
                    "duration": 216,
                    "tags": [
                        {
                            "key": "internal.span.format",
                            "type": "string",
                            "value": "proto"
                        }
                    ],
                    "logs": [],
                    "processID": "p8",
                    "warnings": null
                },
                {
                    "traceID": "573c722ea5ec3c45",
                    "spanID": "8efebda017a512ff",
                    "flags": 1,
                    "operationName": "MmcSetMovieId",
                    "references": [
                        {
                            "refType": "CHILD_OF",
                            "traceID": "573c722ea5ec3c45",
                            "spanID": "736fc26fa6ccc48f"
                        }
                    ],
                    "startTime": 1695223402256494,
                    "duration": 172,
                    "tags": [
                        {
                            "key": "internal.span.format",
                            "type": "string",
                            "value": "proto"
                        }
                    ],
                    "logs": [],
                    "processID": "p8",
                    "warnings": null
                },
                {
                    "traceID": "573c722ea5ec3c45",
                    "spanID": "736fc26fa6ccc48f",
                    "flags": 1,
                    "operationName": "UploadMovieId",
                    "references": [
                        {
                            "refType": "CHILD_OF",
                            "traceID": "573c722ea5ec3c45",
                            "spanID": "6016aaf50cca53b0"
                        }
                    ],
                    "startTime": 1695223402256046,
                    "duration": 9356,
                    "tags": [
                        {
                            "key": "internal.span.format",
                            "type": "string",
                            "value": "proto"
                        }
                    ],
                    "logs": [],
                    "processID": "p8",
                    "warnings": null
                },
                {
                    "traceID": "573c722ea5ec3c45",
                    "spanID": "1ea3c613556d5a82",
                    "flags": 1,
                    "operationName": "UploadText",
                    "references": [
                        {
                            "refType": "CHILD_OF",
                            "traceID": "573c722ea5ec3c45",
                            "spanID": "6016aaf50cca53b0"
                        }
                    ],
                    "startTime": 1695223402255615,
                    "duration": 1995,
                    "tags": [
                        {
                            "key": "internal.span.format",
                            "type": "string",
                            "value": "proto"
                        }
                    ],
                    "logs": [],
                    "processID": "p9",
                    "warnings": null
                },
                {
                    "traceID": "573c722ea5ec3c45",
                    "spanID": "031cc469092cf536",
                    "flags": 1,
                    "operationName": "UploadUniqueId",
                    "references": [
                        {
                            "refType": "CHILD_OF",
                            "traceID": "573c722ea5ec3c45",
                            "spanID": "6016aaf50cca53b0"
                        }
                    ],
                    "startTime": 1695223402255434,
                    "duration": 3420,
                    "tags": [
                        {
                            "key": "internal.span.format",
                            "type": "string",
                            "value": "proto"
                        }
                    ],
                    "logs": [],
                    "processID": "p10",
                    "warnings": null
                }
            ],
            "processes": {
                "p1": {
                    "serviceName": "rating-service",
                    "tags": [
                        {
                            "key": "hostname",
                            "type": "string",
                            "value": "rating-service"
                        },
                        {
                            "key": "ip",
                            "type": "string",
                            "value": "127.0.0.1"
                        },
                        {
                            "key": "jaeger.version",
                            "type": "string",
                            "value": "C++-0.4.2"
                        }
                    ]
                },
                "p10": {
                    "serviceName": "unique-id-service",
                    "tags": [
                        {
                            "key": "hostname",
                            "type": "string",
                            "value": "unique-id-service"
                        },
                        {
                            "key": "ip",
                            "type": "string",
                            "value": "127.0.0.1"
                        },
                        {
                            "key": "jaeger.version",
                            "type": "string",
                            "value": "C++-0.4.2"
                        }
                    ]
                },
                "p2": {
                    "serviceName": "review-storage-service",
                    "tags": [
                        {
                            "key": "hostname",
                            "type": "string",
                            "value": "review-storage-service"
                        },
                        {
                            "key": "ip",
                            "type": "string",
                            "value": "127.0.0.1"
                        },
                        {
                            "key": "jaeger.version",
                            "type": "string",
                            "value": "C++-0.4.2"
                        }
                    ]
                },
                "p3": {
                    "serviceName": "user-service",
                    "tags": [
                        {
                            "key": "hostname",
                            "type": "string",
                            "value": "user-service"
                        },
                        {
                            "key": "ip",
                            "type": "string",
                            "value": "127.0.0.1"
                        },
                        {
                            "key": "jaeger.version",
                            "type": "string",
                            "value": "C++-0.4.2"
                        }
                    ]
                },
                "p4": {
                    "serviceName": "user-review-service",
                    "tags": [
                        {
                            "key": "hostname",
                            "type": "string",
                            "value": "user-review-service"
                        },
                        {
                            "key": "ip",
                            "type": "string",
                            "value": "127.0.0.1"
                        },
                        {
                            "key": "jaeger.version",
                            "type": "string",
                            "value": "C++-0.4.2"
                        }
                    ]
                },
                "p5": {
                    "serviceName": "movie-review-service",
                    "tags": [
                        {
                            "key": "hostname",
                            "type": "string",
                            "value": "movie-review-service"
                        },
                        {
                            "key": "ip",
                            "type": "string",
                            "value": "127.0.0.1"
                        },
                        {
                            "key": "jaeger.version",
                            "type": "string",
                            "value": "C++-0.4.2"
                        }
                    ]
                },
                "p6": {
                    "serviceName": "nginx",
                    "tags": [
                        {
                            "key": "hostname",
                            "type": "string",
                            "value": "nginx-thrift"
                        },
                        {
                            "key": "ip",
                            "type": "string",
                            "value": "127.0.0.1"
                        },
                        {
                            "key": "jaeger.version",
                            "type": "string",
                            "value": "C++-0.4.2"
                        }
                    ]
                },
                "p7": {
                    "serviceName": "compose-review-service",
                    "tags": [
                        {
                            "key": "hostname",
                            "type": "string",
                            "value": "compose-review-service"
                        },
                        {
                            "key": "ip",
                            "type": "string",
                            "value": "127.0.0.1"
                        },
                        {
                            "key": "jaeger.version",
                            "type": "string",
                            "value": "C++-0.4.2"
                        }
                    ]
                },
                "p8": {
                    "serviceName": "movie-id-service",
                    "tags": [
                        {
                            "key": "hostname",
                            "type": "string",
                            "value": "movie-id-service"
                        },
                        {
                            "key": "ip",
                            "type": "string",
                            "value": "127.0.0.1"
                        },
                        {
                            "key": "jaeger.version",
                            "type": "string",
                            "value": "C++-0.4.2"
                        }
                    ]
                },
                "p9": {
                    "serviceName": "text-service",
                    "tags": [
                        {
                            "key": "hostname",
                            "type": "string",
                            "value": "text-service"
                        },
                        {
                            "key": "ip",
                            "type": "string",
                            "value": "127.0.0.1"
                        },
                        {
                            "key": "jaeger.version",
                            "type": "string",
                            "value": "C++-0.4.2"
                        }
                    ]
                }
            },
            "warnings": null
        }
    ],
    "total": 0,
    "limit": 0,
    "offset": 0,
    "errors": null
}